test_opterator
opterator
