Metadata-Version: 1.1
Name: opterator
Version: 0.4
Summary: Easy option parsing introspected from function signature.
Home-page: http://github.com/buchuki/opterator/
Author: Dusty Phillips
Author-email: dusty@buchuki.com
License: MIT
Download-URL: https://github.com/buchuki/opterator/archive/0.4.tar.gz
Keywords: opterator option parse parser options
Platform: UNKNOWN
Classifier: Development Status :: 4 - Beta
Classifier: Intended Audience :: Developers
Classifier: Programming Language :: Python :: 2.6
Classifier: Programming Language :: Python :: 2.7
Classifier: Programming Language :: Python :: 3.3
